adder.v
module adder(
    input [31:0] a,
    input [31:0] b,
    output [31:0] sum
);
    assign sum = a + b;
endmodule

data_memory.v
module data_memory(
    input clk,
    input we,                    // write enable
    input [31:0] addr,           // adres (ALU sonucu)
    input [31:0] wd,             // write data
    output [31:0] rd             // read data
);

    reg [31:0] memory [0:63];    // 64 kelimelik (256 byte) bellek

    always @(posedge clk) begin
        if (we)
            memory[addr[31:2]] <= wd;   // 4-byte hizalı yazma
    end

    assign rd = memory[addr[31:2]];     // her zaman okuma

endmodule

alu.v
module alu (
    input [2:0] alu_control,     // ALU işlemi seçimi
    input [31:0] A, B,           // Giriş operandları
    output reg [31:0] result,    // Çıkış sonucu
    output zero                  // Sonuç sıfır mı?
);

    assign zero = (result == 32'd0);  // ← Şuradaki 'm' hatalıydı, silindi

    always @(*) begin
        case (alu_control)
            3'b000: result = A & B;                         // AND
            3'b001: result = A | B;                         // OR
            3'b010: result = A + B;                         // ADD
            3'b110: result = A - B;                         // SUB
            3'b111: result = (A < B) ? 32'd1 : 32'd0; 
            3'b100: result = A << B[4:0];   //  sll işlemi      // SLT
            default: result = 32'd0;
        endcase
    end

endmodule

reg_file.v
module reg_file (
    input clk,
    input we3,
    input [4:0] a1, a2, a3,
    input [31:0] wd3,
    output [31:0] rd1, rd2
);

    reg [31:0] regs [0:31];

    // Read ports
    assign rd1 = (a1 == 0) ? 32'b0 : regs[a1];
    assign rd2 = (a2 == 0) ? 32'b0 : regs[a2];

    // Write port
    always @(posedge clk) begin
        if (we3 && (a3 != 0))
            regs[a3] <= wd3;
    end

endmodule

imm_gen.v

module imm_gen(
    input clk,
    input [24:0] instr_bits,     // instr[31:7]
    input [1:0] imm_src,         // 00: I-type, 01: S-type, 10: B-type
    output reg [31:0] imm_ext
);

    always @(*) begin
        case (imm_src)
            2'b00: begin // I-type (bits [24:13])
                imm_ext = {{20{instr_bits[24]}}, instr_bits[24:13]};
            end
            2'b01: begin // S-type (bits [24:18] & [4:0])
                imm_ext = {{20{instr_bits[24]}}, instr_bits[24:18], instr_bits[4:0]};
            end
            2'b10: begin // B-type (bits [24], [0], [23:18], [4:1], 0)
                imm_ext = {{19{instr_bits[24]}}, instr_bits[0], instr_bits[23:18], instr_bits[4:1], 1'b0};
            end
            2'b11: begin // J-type (jal)
                // J-type: {instr[31], instr[19:12], instr[20], instr[30:21], 1'b0}
                imm_ext = {{11{instr_bits[24]}},   // sign-extend (instr[31])
                  instr_bits[12:5],       // instr[19:12]
                  instr_bits[13],         // instr[20]
                  instr_bits[23:14],      // instr[30:21]
                  1'b0};
            end
            2'b11: imm_ext = {instr_bits[24:5], 12'b0}; // U-type, instr[31:12] << 12
            default: begin
                imm_ext = 32'd0;
            end
        endcase
    end

endmodule

alu_decoder.v
module alu_decoder (
    input  [1:0] alu_op,
    input  [2:0] funct3,
    input        funct7b5,
    output reg [2:0] alu_control
);

    always @(*) begin
        case (alu_op)
            2'b00: alu_control = 3'b010;  // lw, sw → add
            2'b01: alu_control  = 3'b110;  // beq → subtract
            2'b10: begin                 // R-type veya I-type
                case (funct3)
                    3'b000: alu_control  = (funct7b5 == 1'b1) ? 3'b110 : 3'b010; // sub : add
                    3'b010: alu_control  = 3'b111; // slt
                    3'b110: alu_control= 3'b001; // or
                    3'b111: alu_control  = 3'b000; // and
                    3'b001: alu_control = 3'b100; // sll bu soru icin eklendi
                    default: alu_control = 3'bxxx;
                endcase
            end
            default: alu_control  = 3'bxxx;
        endcase
    end

endmodule

main_decoder.v
module main_decoder (
    input  [6:0] op,
    output reg   reg_write,
    output reg   mem_write,
    output reg   alu_src,
    output reg [1:0] imm_src,
    output reg [1:0] result_src,
    output reg   branch,
    output reg   jump,
    output reg [1:0] alu_op
);

    always @(*) begin
        case (op)
            7'b0000011: begin // lw
                reg_write   = 1;
                mem_write   = 0;
                alu_src     = 1;
                imm_src     = 2'b00;
                result_src  = 2'b01;
                branch      = 0;
                alu_op      = 2'b00;
                jump        = 0;
            end
            7'b0100011: begin // sw
                reg_write   = 0;
                mem_write   = 1;
                alu_src     = 1;
                imm_src     = 2'b01;
                result_src  = 2'b00; // x yerine 00 konur
                branch      = 0;
                alu_op      = 2'b00;
                jump        = 0;
            end
            7'b0110011: begin // R-type
                reg_write   = 1;
                mem_write   = 0;
                alu_src     = 0;
                imm_src     = 2'b00; // x yerine 00
                result_src  = 2'b00;
                branch      = 0;
                alu_op      = 2'b10;
                jump        = 0;
            end
            7'b1100011: begin // beq
                reg_write   = 0;
                mem_write   = 0;
                alu_src     = 0;
                imm_src     = 2'b10;
                result_src  = 2'b00; // x yerine 00
                branch      = 1;
                alu_op      = 2'b01;
                jump        = 0;
            end
            7'b0010011: begin // I-type ALU
                reg_write   = 1;
                mem_write   = 0;
                alu_src     = 1;
                imm_src     = 2'b00;
                result_src  = 2'b00;
                branch      = 0;
                alu_op      = 2'b10;
                jump        = 0;
            end
            7'b1101111: begin // jal
                reg_write   = 1;
                mem_write   = 0;
                alu_src     = 0;        // x yerine default verildi
                imm_src     = 2'b11;
                result_src  = 2'b10;
                branch      = 0;
                alu_op      = 2'b00;    // x yerine default verildi
                jump        = 1;
            end
            7'b0110111: begin // lui
                reg_write   = 1;
                mem_write   = 0;
                alu_src     = 1'bx;
                imm_src     = 2'b11;   // özel U-type
                result_src  = 2'b11;   // yeni: direkt immediate ver
                branch      = 0;
                alu_op      = 2'b00;
                jump        = 0;
            end
            default: begin
                reg_write   = 0;
                mem_write   = 0;
                alu_src     = 0;
                imm_src     = 2'b00;
                result_src  = 2'b00;
                branch      = 0;
                alu_op      = 2'b00;
                jump        = 0;
            end
        endcase
    end

endmodule

control_unit.v
module control_unit (
    input  [6:0] op,
    input  [2:0] funct3,
    input        funct7b5,
    input        zero,


    output pc_src,
    output [1:0] result_src,
    output [2:0] alu_control,
    output mem_write,
    output alu_src,
    output [1:0] imm_src,
    output reg_write
);

    wire branch;
    wire jump;
    wire [1:0] alu_op;

    // Main Decoder instance
    main_decoder md (
        .op(op),
        .reg_write(reg_write),
        .mem_write(mem_write),
        .alu_src(alu_src),
        .imm_src(imm_src),
        .result_src(result_src),
        .branch(branch),
        .jump(jump),
        .alu_op(alu_op)
    );

    // ALU Decoder instance
    alu_decoder ad (
        .alu_op(alu_op),
        .funct3(funct3),
        .funct7b5(funct7b5),
        .alu_control(alu_control)
    );

    assign pc_src = (branch & zero) | jump;


endmodule

instr_mem.v
module instr_mem(
    input [31:0] addr,           // PC'den gelen adres
    output [31:0] instr          // Çıkan komut
);
    reg [31:0] memory [0:63];    // 16 komutluk küçük bir bellek

    // initial begin
    //     // Belleğe örnek komutlar (gerçek opcode'lar değil)
    //     $readmemh("instr_mem.mem", memory); // Belleği dosyadan yükle
    // end

    assign instr = memory[addr[31:2]];  // 4-byte hizalı adresleme
endmodule

pc.v
module pc(
    input clk,
    input reset,
    input [31:0] pc_next,
    output reg [31:0] pc_out
);
    always @(posedge clk or posedge reset) begin
        if (reset)
            pc_out <= 32'd0;
        else
            pc_out <= pc_next;
    end
endmodule

top.v
module top (
    input clk,
    input reset
);

    // === Program Counter ===
    wire [31:0] pc_current;
    wire [31:0] pc_next;
    wire [31:0] pc_plus4;

    pc program_counter (
        .clk(clk),
        .reset(reset),
        .pc_next(pc_next),
        .pc_out(pc_current)
    );

    // === Instruction Memory ===
    wire [31:0] instr;

    instr_mem imem (
        .addr(pc_current),
        .instr(instr)
    );

    // === Instruction Fields ===
    wire [6:0]  op      = instr[6:0];
    wire [4:0]  rd      = instr[11:7];
    wire [2:0]  funct3  = instr[14:12];
    wire [4:0]  rs1     = instr[19:15];
    wire [4:0]  rs2     = instr[24:20];
    wire        funct7b5 = instr[30];
    

    // === Control Unit ===
    wire        reg_write, mem_write, alu_src;
    wire [1:0]  imm_src, result_src;
    wire        pc_src;
    wire [2:0]  alu_control;

    control_unit cu (
        .op(op),
        .funct3(funct3),
        .funct7b5(funct7b5),
        .zero(zero),
        .reg_write(reg_write),
        .mem_write(mem_write),
        .alu_src(alu_src),
        .imm_src(imm_src),
        .result_src(result_src),
        .pc_src(pc_src),
        .alu_control(alu_control)
    );
    
    // === Immediate Generator ===
    wire [31:0] imm_ext;

    imm_gen immgen (
        .instr_bits(instr[31:7]),
        .imm_src(imm_src),
        .imm_ext(imm_ext)
    );

    // === Register File ===
    wire [31:0] rd1, rd2;

    reg_file rf (
        .clk(clk),
        .we3(reg_write),
        .a1(rs1),
        .a2(rs2),
        .a3(rd),
        .wd3(result),
        .rd1(rd1),
        .rd2(rd2)
    );

    // === ALU ===
    wire [31:0] src_b, alu_result;
    wire zero;

    assign src_b = (alu_src) ? imm_ext : rd2;

    alu alu_unit (
        .A(rd1),
        .B(src_b),
        .alu_control(alu_control),
        .result(alu_result),
        .zero(zero)
    );

    // === Data Memory ===
    wire [31:0] read_data;

    data_memory dmem (
        .clk(clk),
        .addr(alu_result),
        .wd(rd2),
        .we(mem_write),
        .rd(read_data)
    );

    // === Result Mux ===
    wire [31:0] result;

    assign result =
        (result_src == 2'b00) ? alu_result :
        (result_src == 2'b01) ? read_data  :
        (result_src == 2'b10) ? pc_plus4   :
        (result_src == 2'b11) ? imm_ext    : 
        32'b0;

    // === PC Adder: PC + 4 and PC + imm ===
    adder pc_add4 (
        .a(pc_current),
        .b(32'd4),
        .sum(pc_plus4)
    );

    wire [31:0] pc_target;

    adder pc_branch (
        .a(pc_current),
        .b(imm_ext),
        .sum(pc_target)
    );

    assign pc_next = (pc_src) ? pc_target : pc_plus4;

endmodule

answer3_tb.v
`timescale 1ns/1ps

module answer3_tb;

    reg clk = 0;
    reg reset = 1;

    top uut (
        .clk(clk),
        .reset(reset)
    );

    // Clock üretimi
    always #5 clk = ~clk;

    initial begin
        // === instr_mem belleğini buradan doldur ===
        uut.imem.memory[0] = 32'h00045b37;  // lui x11, 0x00045 → x11 = 0x00045000
        uut.imem.memory[1] = 32'h0012b337;  // lui x6,  0x00123 → x6  = 0x00123000
        uut.imem.memory[2] = 32'h000ab3b7;  // lui x7,  0x000AB → x7  = 0x000AB000
        uut.imem.memory[3] = 32'h00000013;  // nop (addi x0, x0, 0)

        $dumpfile("answer3_tb.vcd");
        $dumpvars(0, answer3_tb);

        #10 reset = 0;

        // Programın çalışmasına zaman tanı
        #200;

        $finish;
    end

endmodule

answer3_tb.vcd
$date
	Tue May 06 20:41:35 2025
$end
$version
	Icarus Verilog
$end
$timescale
	1ps
$end
$scope module answer3_tb $end
$var reg 1 ! clk $end
$var reg 1 " reset $end
$scope module uut $end
$var wire 1 ! clk $end
$var wire 1 " reset $end
$var wire 1 # zero $end
$var wire 32 $ src_b [31:0] $end
$var wire 5 % rs2 [4:0] $end
$var wire 5 & rs1 [4:0] $end
$var wire 2 ' result_src [1:0] $end
$var wire 32 ( result [31:0] $end
$var wire 1 ) reg_write $end
$var wire 32 * read_data [31:0] $end
$var wire 32 + rd2 [31:0] $end
$var wire 32 , rd1 [31:0] $end
$var wire 5 - rd [4:0] $end
$var wire 32 . pc_target [31:0] $end
$var wire 1 / pc_src $end
$var wire 32 0 pc_plus4 [31:0] $end
$var wire 32 1 pc_next [31:0] $end
$var wire 32 2 pc_current [31:0] $end
$var wire 7 3 op [6:0] $end
$var wire 1 4 mem_write $end
$var wire 32 5 instr [31:0] $end
$var wire 2 6 imm_src [1:0] $end
$var wire 32 7 imm_ext [31:0] $end
$var wire 1 8 funct7b5 $end
$var wire 3 9 funct3 [2:0] $end
$var wire 1 : alu_src $end
$var wire 32 ; alu_result [31:0] $end
$var wire 3 < alu_control [2:0] $end
$scope module alu_unit $end
$var wire 32 = B [31:0] $end
$var wire 1 # zero $end
$var wire 3 > alu_control [2:0] $end
$var wire 32 ? A [31:0] $end
$var reg 32 @ result [31:0] $end
$upscope $end
$scope module cu $end
$var wire 3 A funct3 [2:0] $end
$var wire 1 8 funct7b5 $end
$var wire 7 B op [6:0] $end
$var wire 1 / pc_src $end
$var wire 1 # zero $end
$var wire 2 C result_src [1:0] $end
$var wire 1 ) reg_write $end
$var wire 1 4 mem_write $end
$var wire 1 D jump $end
$var wire 2 E imm_src [1:0] $end
$var wire 1 F branch $end
$var wire 1 : alu_src $end
$var wire 2 G alu_op [1:0] $end
$var wire 3 H alu_control [2:0] $end
$scope module ad $end
$var wire 3 I funct3 [2:0] $end
$var wire 1 8 funct7b5 $end
$var wire 2 J alu_op [1:0] $end
$var reg 3 K alu_control [2:0] $end
$upscope $end
$scope module md $end
$var wire 7 L op [6:0] $end
$var reg 2 M alu_op [1:0] $end
$var reg 1 : alu_src $end
$var reg 1 F branch $end
$var reg 2 N imm_src [1:0] $end
$var reg 1 D jump $end
$var reg 1 4 mem_write $end
$var reg 1 ) reg_write $end
$var reg 2 O result_src [1:0] $end
$upscope $end
$upscope $end
$scope module dmem $end
$var wire 32 P addr [31:0] $end
$var wire 1 ! clk $end
$var wire 32 Q rd [31:0] $end
$var wire 1 4 we $end
$var wire 32 R wd [31:0] $end
$upscope $end
$scope module imem $end
$var wire 32 S instr [31:0] $end
$var wire 32 T addr [31:0] $end
$upscope $end
$scope module immgen $end
$var wire 1 U clk $end
$var wire 2 V imm_src [1:0] $end
$var wire 25 W instr_bits [24:0] $end
$var reg 32 X imm_ext [31:0] $end
$upscope $end
$scope module pc_add4 $end
$var wire 32 Y b [31:0] $end
$var wire 32 Z sum [31:0] $end
$var wire 32 [ a [31:0] $end
$upscope $end
$scope module pc_branch $end
$var wire 32 \ b [31:0] $end
$var wire 32 ] sum [31:0] $end
$var wire 32 ^ a [31:0] $end
$upscope $end
$scope module program_counter $end
$var wire 1 ! clk $end
$var wire 32 _ pc_next [31:0] $end
$var wire 1 " reset $end
$var reg 32 ` pc_out [31:0] $end
$upscope $end
$scope module rf $end
$var wire 5 a a1 [4:0] $end
$var wire 5 b a2 [4:0] $end
$var wire 5 c a3 [4:0] $end
$var wire 1 ! clk $end
$var wire 32 d wd3 [31:0] $end
$var wire 1 ) we3 $end
$var wire 32 e rd2 [31:0] $end
$var wire 32 f rd1 [31:0] $end
$upscope $end
$upscope $end
$upscope $end
$enddefinitions $end
$comment Show the parameter values. $end
$dumpall
$end
#0
$dumpvars
bx f
b0 e
b1000101000000000000 d
b10110 c
b0 b
b1000 a
b0 `
b100 _
b0 ^
b1000101000000000000 ]
b1000101000000000000 \
b0 [
b100 Z
b100 Y
b1000101000000000000 X
b100010110110 W
b11 V
zU
b0 T
b1000101101100110111 S
b0 R
bx Q
bx P
b11 O
b11 N
b0 M
b110111 L
b10 K
b0 J
b101 I
b10 H
b0 G
0F
b11 E
0D
b11 C
b110111 B
b101 A
bx @
bx ?
b10 >
b0x000x0x000000000000 =
b10 <
bx ;
x:
b101 9
08
b1000101000000000000 7
b11 6
b1000101101100110111 5
04
b110111 3
b0 2
b100 1
b100 0
0/
b1000101000000000000 .
b10110 -
bx ,
b0 +
bx *
1)
b1000101000000000000 (
b11 '
b1000 &
b0 %
b0x000x0x000000000000 $
x#
1"
0!
$end
#5000
1!
#10000
0!
0"
#15000
b101011100000000000 (
b101011100000000000 d
bx $
bx =
b101011100000000000 7
b101011100000000000 X
b101011100000000000 \
bx +
bx R
bx e
b10010101100110 W
b1 %
b1 b
b101 &
b101 a
b11 9
b11 A
b11 I
b110 -
b110 c
b1000 1
b1000 _
b100101011001100110111 5
b100101011001100110111 S
b101011100000000100 .
b101011100000000100 ]
b1000 0
b1000 Z
b100 2
b100 T
b100 [
b100 ^
b100 `
1!
#20000
0!
#25000
b10101011000000000000 (
b10101011000000000000 d
b0x0x0x0xx000000000000 $
b0x0x0x0xx000000000000 =
b10101011000000000000 7
b10101011000000000000 X
b10101011000000000000 \
b0 +
b0 R
b0 e
b1010101100111 W
b0 %
b0 b
b10101 &
b10101 a
b111 -
b111 c
b1100 1
b1100 _
b10101011001110110111 5
b10101011001110110111 S
b10101011000000001000 .
b10101011000000001000 ]
b1100 0
b1100 Z
b1000 2
b1000 T
b1000 [
b1000 ^
b1000 `
1!
#30000
0!
#35000
1#
b0 ;
b0 @
b0 P
b0 (
b0 d
b0 $
b0 =
b0 7
b0 X
b0 \
b0 ,
b0 ?
b0 f
b10 G
b10 J
b10 M
b0 '
b0 C
b0 O
b0 6
b0 E
b0 N
b0 V
1:
b0 W
b0 &
b0 a
b0 9
b0 A
b0 I
b0 -
b0 c
b10011 3
b10011 B
b10011 L
b10000 1
b10000 _
b10011 5
b10011 S
b1100 .
b1100 ]
b10000 0
b10000 Z
b1100 2
b1100 T
b1100 [
b1100 ^
b1100 `
1!
#40000
0!
#45000
bx (
bx d
x#
bx ;
bx @
bx P
bx $
bx =
bx 7
bx X
bx \
bx +
bx R
bx e
bx ,
bx ?
bx f
b0 G
b0 J
b0 M
0:
0)
bx W
x8
bx %
bx b
bx &
bx a
bx 9
bx A
bx I
bx -
bx c
bx 3
bx B
bx L
b10100 1
b10100 _
bx 5
bx S
bx .
bx ]
b10100 0
b10100 Z
b10000 2
b10000 T
b10000 [
b10000 ^
b10000 `
1!
#50000
0!
#55000
b11000 1
b11000 _
b11000 0
b11000 Z
b10100 2
b10100 T
b10100 [
b10100 ^
b10100 `
1!
#60000
0!
#65000
b11100 1
b11100 _
b11100 0
b11100 Z
b11000 2
b11000 T
b11000 [
b11000 ^
b11000 `
1!
#70000
0!
#75000
b100000 1
b100000 _
b100000 0
b100000 Z
b11100 2
b11100 T
b11100 [
b11100 ^
b11100 `
1!
#80000
0!
#85000
b100100 1
b100100 _
b100100 0
b100100 Z
b100000 2
b100000 T
b100000 [
b100000 ^
b100000 `
1!
#90000
0!
#95000
b101000 1
b101000 _
b101000 0
b101000 Z
b100100 2
b100100 T
b100100 [
b100100 ^
b100100 `
1!
#100000
0!
#105000
b101100 1
b101100 _
b101100 0
b101100 Z
b101000 2
b101000 T
b101000 [
b101000 ^
b101000 `
1!
#110000
0!
#115000
b110000 1
b110000 _
b110000 0
b110000 Z
b101100 2
b101100 T
b101100 [
b101100 ^
b101100 `
1!
#120000
0!
#125000
b110100 1
b110100 _
b110100 0
b110100 Z
b110000 2
b110000 T
b110000 [
b110000 ^
b110000 `
1!
#130000
0!
#135000
b111000 1
b111000 _
b111000 0
b111000 Z
b110100 2
b110100 T
b110100 [
b110100 ^
b110100 `
1!
#140000
0!
#145000
b111100 1
b111100 _
b111100 0
b111100 Z
b111000 2
b111000 T
b111000 [
b111000 ^
b111000 `
1!
#150000
0!
#155000
b1000000 1
b1000000 _
b1000000 0
b1000000 Z
b111100 2
b111100 T
b111100 [
b111100 ^
b111100 `
1!
#160000
0!
#165000
b1000100 1
b1000100 _
b1000100 0
b1000100 Z
b1000000 2
b1000000 T
b1000000 [
b1000000 ^
b1000000 `
1!
#170000
0!
#175000
b1001000 1
b1001000 _
b1001000 0
b1001000 Z
b1000100 2
b1000100 T
b1000100 [
b1000100 ^
b1000100 `
1!
#180000
0!
#185000
b1001100 1
b1001100 _
b1001100 0
b1001100 Z
b1001000 2
b1001000 T
b1001000 [
b1001000 ^
b1001000 `
1!
#190000
0!
#195000
b1010000 1
b1010000 _
b1010000 0
b1010000 Z
b1001100 2
b1001100 T
b1001100 [
b1001100 ^
b1001100 `
1!
#200000
0!
#205000
b1010100 1
b1010100 _
b1010100 0
b1010100 Z
b1010000 2
b1010000 T
b1010000 [
b1010000 ^
b1010000 `
1!
